pyparadox/__init__.py
pyparadox/config.py
pyparadox/core.py
pyparadox/gui.py
pyparadox/main.py
pyparadox/resources/ck2.png
pyparadox/resources/eu4.png
pyparadox/resources/logging.json
pyparadox/resources/paradox.png
pyparadox/resources/stellaris.png
pyparadox/resources/ui/ConfigDlg.ui
pyparadox/resources/ui/MainWindow.ui
pyparadox/resources/ui/PluginListView.qml
pyparadox/resources/ui/main.qml
pyparadox-0.3.10.dist-info/DESCRIPTION.rst
pyparadox-0.3.10.dist-info/METADATA
pyparadox-0.3.10.dist-info/RECORD
pyparadox-0.3.10.dist-info/WHEEL
pyparadox-0.3.10.dist-info/entry_points.txt
pyparadox-0.3.10.dist-info/metadata.json
pyparadox-0.3.10.dist-info/top_level.txt
