Metadata-Version: 2.0
Name: pyparadox
Version: 0.3.10
Summary: PyParadox is a nix launcher for Paradox titles.
Home-page: https://gitlab.com/carmenbbakker/pyparadox
Author: Carmen Bianca Bakker
Author-email: c.b.bakker@carmenbianca.eu
License: GPLv3+
Keywords: pyparadox
Platform: UNKNOWN
Classifier: Development Status :: 5 - Production/Stable
Classifier: Environment :: X11 Applications :: Qt
Classifier: Intended Audience :: End Users/Desktop
Classifier: License :: OSI Approved :: GNU General Public License v3 or later (GPLv3+)
Classifier: Natural Language :: English
Classifier: Programming Language :: Python :: 3
Classifier: Programming Language :: Python :: 3.3
Classifier: Programming Language :: Python :: 3.4
Classifier: Programming Language :: Python :: 3.5
Classifier: Programming Language :: Python :: 3 :: Only
Classifier: Topic :: Games/Entertainment
Classifier: Topic :: Utilities
Requires-Dist: appdirs
